{
    "artist": "Maria Tabarcea",
    "backgroundColor": "#3d4c6c",
    "path": "",
    "released": 2020,
    "album": "lettering",
    "views": 
    [
        { 
            "id": 1,
            "album": "lettering",  
            "path": "", 
            "title": "CITY GONE WILD" 
        },
        { 
            "id": 2,
            "album": "lettering",  
            "path": "", 
            "title": "In the streets Bloguluotrava" 
        },
        { 
            "id": 3,
            "album": "lettering",  
            "path": "", 
            "title": "Each for equal" 
        },
        { 
            "id": 4,
            "album": "lettering",  
            "path": "", 
            "title": "Happy easter" 
        },
        { 
            "id": 5,
            "album": "lettering",  
            "path": "", 
            "title": "hohoho" 
        },
        { 
            "id": 6,
            "album": "lettering",  
            "path": "", 
            "title": "Insert quote" 
        },
        { 
            "id": 7,
            "album": "lettering",  
            "path": "", 
            "title": "Is it big enough?" 
        }
    ]
  }
  